doutline/VERSION
doutline/__init__.py
doutline/exceptions.py
doutline/outline.py
doutline/py.typed
doutline/types.py
doutline/writers/__init__.py
doutline/writers/html.py
doutline/writers/markdown.py
doutline/writers/py.typed
doutline/writers/utils.py
doutline-1.0.0a3.dist-info/LICENSE
doutline-1.0.0a3.dist-info/METADATA
doutline-1.0.0a3.dist-info/WHEEL
doutline-1.0.0a3.dist-info/top_level.txt
doutline-1.0.0a3.dist-info/RECORD
